PT104/__init__.py
pico_pt104-1.0.0.dist-info/METADATA
pico_pt104-1.0.0.dist-info/RECORD
pico_pt104-1.0.0.dist-info/WHEEL
pico_pt104-1.0.0.dist-info/top_level.txt
