Metadata-Version: 2.1
Name: pico-pt104
Version: 1.0.0
Summary: A Python Wrapper for the usbpt104 library from Pico
Home-page: http://www.github.com/trombastic/Pico_PT104
Author: Martin Schröder
Author-email: m.schroeder@tu-berlin.de
License: GPL version 3
Platform: OS Independent
Classifier: Development Status :: 4 - Beta
Classifier: Environment :: Console
Classifier: Intended Audience :: Developers
Classifier: Intended Audience :: Science/Research
Classifier: License :: OSI Approved :: GNU General Public License v3 (GPLv3)
Classifier: Operating System :: POSIX
Classifier: Operating System :: MacOS :: MacOS X
Classifier: Programming Language :: Python
Classifier: Programming Language :: JavaScript
